pyconbg.py
pyconbg/__init__.py
pyconbg/cli/__init__.py
pyconbg/cli/app.py
pyconbg-0.1.9.dist-info/LICENSE
pyconbg-0.1.9.dist-info/METADATA
pyconbg-0.1.9.dist-info/WHEEL
pyconbg-0.1.9.dist-info/entry_points.txt
pyconbg-0.1.9.dist-info/top_level.txt
pyconbg-0.1.9.dist-info/RECORD
