Metadata-Version: 2.1
Name: pyconbg
Version: 0.1.9
Summary: Generate an icon pattern background
Home-page: https://github.com/Fraccs/pyconbg
Author: Francesco Cristiano Aliprandi
Author-email: aliprandifrancescopp@gmail.com
Requires-Python: >=3.10
License-File: LICENSE
